pypixplore
