Metadata-Version: 1.1
Name: pypixplore
Version: 0.2.2
Summary: Explore PyPI and visualize its contents in unusual and interesting ways
Home-page: http://github.com/fccoelho/pypixplorer
Author: Flavio C. Coelho and colaborators
Author-email: fccoelho@gmail.com
License: GPLv3
Platform: UNKNOWN
Classifier: Development Status :: 4 - Beta
Classifier: Programming Language :: Python
